LICENSE.txt
MANIFEST.in
README.md
README.rst
requirements.txt
setup.cfg
setup.py
reposify/__init__.py
reposify/exceptions.py
reposify.egg-info/PKG-INFO
reposify.egg-info/SOURCES.txt
reposify.egg-info/dependency_links.txt
reposify.egg-info/requires.txt
reposify.egg-info/top_level.txt
tests/__init__.py
tests/test_api.py
tests/test_requirements.txt
tests/mock_get_responses/account_status.json
tests/mock_get_responses/insights_count.json
tests/mock_get_responses/insights_search.json
tests/mock_get_responses/scan_host.json
tests/mock_get_responses/scan_internet.json
tests/mock_get_responses/scan_status.json